{
  "name": "cooking-for-myself-data",
  "version": "0.1.0",
  "generatedAt": "2026-05-22T00:00:00.000Z",
  "sourceRunId": "global-520-expansion",
  "approvedAt": "2026-05-16",
  "canonicalLanguages": [
    "zhHant",
    "zhHans",
    "en",
    "ja",
    "ko",
    "th",
    "vi",
    "id",
    "tl"
  ],
  "counts": {
    "ingredients": 85,
    "meals": 520
  },
  "licenses": {
    "data": "ODC-BY-1.0",
    "images": "CC-BY-4.0",
    "code": "MIT"
  },
  "recordOrder": [
    "tomato-egg",
    "garlic-choy-sum",
    "soy-wings",
    "steamed-egg",
    "ginger-scallion-fish",
    "beef-gai-lan",
    "tofu-minced-pork",
    "chicken-congee",
    "wonton-noodle",
    "napa-tofu-pot",
    "claypot-chicken-rice",
    "scallion-oil-noodles",
    "salt-pepper-pork-chop",
    "black-bean-chicken",
    "steamed-pork-patty",
    "bitter-melon-beef",
    "shrimp-scrambled-egg",
    "char-siu-egg-rice",
    "satay-beef-noodles",
    "baked-pork-chop-rice",
    "curry-fish-balls-rice",
    "corn-fish-fillet-rice",
    "hong-kong-borscht",
    "lotus-root-pork-soup",
    "winter-melon-soup",
    "watercress-soup",
    "steamed-chicken-rice",
    "mapo-tofu-hk",
    "eggplant-minced-pork",
    "hoisin-chicken-lettuce",
    "stir-fried-rice-noodles-beef",
    "yangzhou-fried-rice",
    "steamed-garlic-shrimp",
    "garlic-scallion-oil-chicken-rice",
    "steamed-black-bean-spare-ribs-rice",
    "rice-cooker-baked-chicken-rice",
    "pan-fried-turnip-cake-egg",
    "shaoxing-wine-chicken-rice",
    "luncheon-meat-egg-macaroni",
    "curry-beef-brisket-rice",
    "roast-pork-rice",
    "cheung-fun-breakfast-plate",
    "sesame-shrimp-toast-plate",
    "oyakodon",
    "teriyaki-salmon",
    "japanese-curry-rice",
    "miso-soup-rice-set",
    "gyudon",
    "onigiri-trio",
    "omurice",
    "yakisoba",
    "karaage-rice-plate",
    "okonomiyaki",
    "katsudon",
    "soboro-don",
    "yaki-udon",
    "zaru-soba-set",
    "tonkatsu-rice-plate",
    "kimchi-fried-rice",
    "bulgogi-rice-bowl",
    "soondubu-jjigae",
    "bibimbap",
    "tteokbokki-skillet",
    "kimbap-lunchbox",
    "dakgangjeong-rice-plate",
    "gyeran-mari-rice-set",
    "japchae-noodle-bowl",
    "kimchi-jjigae",
    "jajangmyeon",
    "haemul-pajeon",
    "dubu-jorim-rice",
    "kongnamul-bap",
    "lu-rou-fan",
    "taiwanese-beef-noodle-soup",
    "three-cup-chicken-rice",
    "taiwanese-pork-chop-bento",
    "oyster-omelette-plate",
    "danzai-noodles",
    "scallion-pancake-egg-wrap",
    "taiwanese-popcorn-chicken-rice",
    "garlic-sweet-potato-leaves-rice-set",
    "lu-wei-rice-plate",
    "pad-kra-pao",
    "thai-green-curry",
    "pad-thai",
    "pho-ga",
    "lemongrass-chicken-rice",
    "goi-cuon-dinner",
    "miso-salmon-soba-bowl",
    "kimchi-tofu-egg-rice-bowl",
    "ginger-scallion-chicken-rice-bowl",
    "teriyaki-salmon-cucumber-rice-bowl",
    "shrimp-soba-cucumber-bowl",
    "tofu-egg-bibimbap-bowl",
    "lemongrass-chicken-rice-noodle-bowl",
    "tomato-egg-tofu-udon",
    "deconstructed-kimbap-bowl",
    "salmon-onigiri-plate",
    "gochujang-tofu-lettuce-cups",
    "shrimp-rice-paper-noodle-rolls",
    "cold-soba-tofu-set",
    "chicken-lettuce-rice-wraps",
    "miso-salmon-rice-soup",
    "napa-tofu-egg-drop-soup",
    "kimchi-tofu-rice-soup",
    "chicken-soba-broth-bowl",
    "tomato-tofu-egg-soup",
    "ginger-white-fish-rice-soup",
    "teriyaki-chicken-rice-lunchbox",
    "sweet-potato-leaves-tofu-rice-set",
    "chicken-soboro-cucumber-rice-box",
    "gochujang-chicken-rice-box",
    "chicken-ginger-rice-bowl",
    "chicken-noodle-soup",
    "chicken-garlic-vegetable-rice",
    "chicken-soy-glaze-plate",
    "chicken-quick-curry-noodles",
    "chicken-lettuce-cup-dinner",
    "tofu-ginger-rice-bowl",
    "tofu-noodle-soup",
    "chicken-ginger-rice-bowl-chinese",
    "chicken-noodle-soup-chinese",
    "chicken-garlic-vegetable-rice-chinese",
    "chicken-soy-glaze-plate-chinese",
    "chicken-quick-curry-noodles-chinese",
    "chicken-lettuce-cup-dinner-chinese",
    "tofu-ginger-rice-bowl-chinese",
    "tofu-noodle-soup-chinese",
    "tofu-garlic-vegetable-rice",
    "tofu-soy-glaze-plate",
    "chicken-ginger-rice-bowl-japanese",
    "chicken-noodle-soup-japanese",
    "chicken-garlic-vegetable-rice-japanese",
    "chicken-soy-glaze-plate-japanese",
    "chicken-quick-curry-noodles-japanese",
    "chicken-lettuce-cup-dinner-japanese",
    "tofu-ginger-rice-bowl-japanese",
    "tofu-noodle-soup-japanese",
    "tofu-garlic-vegetable-rice-japanese",
    "tofu-soy-glaze-plate-japanese",
    "chicken-ginger-rice-bowl-korean",
    "chicken-noodle-soup-korean",
    "chicken-garlic-vegetable-rice-korean",
    "chicken-soy-glaze-plate-korean",
    "chicken-quick-curry-noodles-korean",
    "chicken-lettuce-cup-dinner-korean",
    "tofu-ginger-rice-bowl-korean",
    "tofu-noodle-soup-korean",
    "chicken-ginger-rice-bowl-thai",
    "chicken-noodle-soup-thai",
    "chicken-garlic-vegetable-rice-thai",
    "chicken-soy-glaze-plate-thai",
    "chicken-quick-curry-noodles-thai",
    "chicken-lettuce-cup-dinner-thai",
    "tofu-ginger-rice-bowl-thai",
    "tofu-noodle-soup-thai",
    "chicken-ginger-rice-bowl-vietnamese",
    "chicken-noodle-soup-vietnamese",
    "chicken-garlic-vegetable-rice-vietnamese",
    "chicken-soy-glaze-plate-vietnamese",
    "chicken-quick-curry-noodles-vietnamese",
    "chicken-lettuce-cup-dinner-vietnamese",
    "tofu-ginger-rice-bowl-vietnamese",
    "tofu-noodle-soup-vietnamese",
    "chicken-ginger-rice-bowl-taiwanese",
    "chicken-noodle-soup-taiwanese",
    "chicken-garlic-vegetable-rice-taiwanese",
    "chicken-soy-glaze-plate-taiwanese",
    "chicken-quick-curry-noodles-taiwanese",
    "chicken-lettuce-cup-dinner-taiwanese",
    "chicken-tomato-basil-pasta",
    "chicken-pesto-pasta",
    "chicken-lemon-risotto",
    "chicken-minestrone-bowl",
    "chicken-polenta-skillet",
    "chicken-parmesan-pasta",
    "mushroom-tomato-basil-pasta",
    "mushroom-pesto-pasta",
    "mushroom-lemon-risotto",
    "mushroom-minestrone-bowl",
    "mushroom-polenta-skillet",
    "mushroom-parmesan-pasta",
    "ground-beef-tomato-basil-pasta",
    "ground-beef-pesto-pasta",
    "ground-beef-lemon-risotto",
    "ground-beef-minestrone-bowl",
    "ground-beef-polenta-skillet",
    "ground-beef-parmesan-pasta",
    "salmon-tomato-basil-pasta",
    "salmon-pesto-pasta",
    "salmon-lemon-risotto",
    "salmon-minestrone-bowl",
    "salmon-polenta-skillet",
    "salmon-parmesan-pasta",
    "shrimp-tomato-basil-pasta",
    "chicken-dijon-skillet",
    "chicken-proven-al-stew",
    "chicken-mushroom-fricassee",
    "chicken-potato-gratin-plate",
    "chicken-lentil-bistro-bowl",
    "mushroom-dijon-skillet",
    "mushroom-proven-al-stew",
    "mushroom-mushroom-fricassee",
    "mushroom-potato-gratin-plate",
    "mushroom-lentil-bistro-bowl",
    "ground-beef-dijon-skillet",
    "ground-beef-proven-al-stew",
    "ground-beef-mushroom-fricassee",
    "ground-beef-potato-gratin-plate",
    "ground-beef-lentil-bistro-bowl",
    "salmon-dijon-skillet",
    "salmon-proven-al-stew",
    "salmon-mushroom-fricassee",
    "salmon-potato-gratin-plate",
    "salmon-lentil-bistro-bowl",
    "chicken-paella-style-rice",
    "chicken-paprika-potato-skillet",
    "chicken-tomato-chickpea-stew",
    "chicken-garlic-rice-plate",
    "chicken-pepper-tortilla-plate",
    "mushroom-paella-style-rice",
    "mushroom-paprika-potato-skillet",
    "mushroom-tomato-chickpea-stew",
    "mushroom-garlic-rice-plate",
    "mushroom-pepper-tortilla-plate",
    "ground-beef-paella-style-rice",
    "ground-beef-paprika-potato-skillet",
    "ground-beef-tomato-chickpea-stew",
    "ground-beef-garlic-rice-plate",
    "ground-beef-pepper-tortilla-plate",
    "salmon-paella-style-rice",
    "salmon-paprika-potato-skillet",
    "salmon-tomato-chickpea-stew",
    "chicken-lemon-herb-bowl",
    "chicken-feta-vegetable-plate",
    "chicken-pita-salad-plate",
    "chicken-tomato-eggplant-bake",
    "chicken-yogurt-rice-bowl",
    "chickpea-lemon-herb-bowl",
    "chickpea-feta-vegetable-plate",
    "chickpea-pita-salad-plate",
    "chickpea-tomato-eggplant-bake",
    "chickpea-yogurt-rice-bowl",
    "lamb-lemon-herb-bowl",
    "lamb-feta-vegetable-plate",
    "lamb-pita-salad-plate",
    "lamb-tomato-eggplant-bake",
    "lamb-yogurt-rice-bowl",
    "shrimp-lemon-herb-bowl",
    "shrimp-feta-vegetable-plate",
    "shrimp-pita-salad-plate",
    "shrimp-tomato-eggplant-bake",
    "shrimp-yogurt-rice-bowl",
    "chicken-paprika-stew",
    "chicken-cabbage-skillet",
    "chicken-mushroom-potato-plate",
    "chicken-dill-yogurt-bowl",
    "chicken-noodle-casserole",
    "mushroom-paprika-stew",
    "mushroom-cabbage-skillet",
    "mushroom-mushroom-potato-plate",
    "mushroom-dill-yogurt-bowl",
    "mushroom-noodle-casserole",
    "ground-beef-paprika-stew",
    "ground-beef-cabbage-skillet",
    "ground-beef-mushroom-potato-plate",
    "ground-beef-dill-yogurt-bowl",
    "ground-beef-noodle-casserole",
    "salmon-paprika-stew",
    "salmon-cabbage-skillet",
    "salmon-mushroom-potato-plate",
    "salmon-dill-yogurt-bowl",
    "salmon-noodle-casserole",
    "shrimp-paprika-stew",
    "shrimp-cabbage-skillet",
    "chicken-chili-bowl",
    "chicken-sheet-pan-dinner",
    "chicken-rice-power-bowl",
    "chicken-mac-and-vegetable-bake",
    "chicken-barbecue-skillet",
    "turkey-chili-bowl",
    "turkey-sheet-pan-dinner",
    "turkey-rice-power-bowl",
    "turkey-mac-and-vegetable-bake",
    "turkey-barbecue-skillet",
    "beef-chili-bowl",
    "beef-sheet-pan-dinner",
    "beef-rice-power-bowl",
    "beef-mac-and-vegetable-bake",
    "beef-barbecue-skillet",
    "salmon-chili-bowl",
    "salmon-sheet-pan-dinner",
    "salmon-rice-power-bowl",
    "salmon-mac-and-vegetable-bake",
    "salmon-barbecue-skillet",
    "tuna-chili-bowl",
    "tuna-sheet-pan-dinner",
    "tuna-rice-power-bowl",
    "tuna-mac-and-vegetable-bake",
    "tuna-barbecue-skillet",
    "chicken-grain-bowl",
    "chicken-creamy-pasta-skillet",
    "chicken-roasted-vegetable-plate",
    "chicken-tomato-rice-bake",
    "chicken-quick-supper-bowl",
    "mushroom-grain-bowl",
    "mushroom-creamy-pasta-skillet",
    "mushroom-roasted-vegetable-plate",
    "mushroom-tomato-rice-bake",
    "mushroom-quick-supper-bowl",
    "ground-beef-grain-bowl",
    "ground-beef-creamy-pasta-skillet",
    "ground-beef-roasted-vegetable-plate",
    "ground-beef-tomato-rice-bake",
    "ground-beef-quick-supper-bowl",
    "salmon-grain-bowl",
    "salmon-creamy-pasta-skillet",
    "salmon-roasted-vegetable-plate",
    "salmon-tomato-rice-bake",
    "salmon-quick-supper-bowl",
    "chicken-market-vegetable-stew",
    "chicken-herb-potato-tray",
    "chicken-rustic-pasta-bake",
    "chicken-bean-and-greens-bowl",
    "chicken-farmhouse-skillet",
    "mushroom-market-vegetable-stew",
    "mushroom-herb-potato-tray",
    "mushroom-rustic-pasta-bake",
    "mushroom-bean-and-greens-bowl",
    "mushroom-farmhouse-skillet",
    "ground-beef-market-vegetable-stew",
    "ground-beef-herb-potato-tray",
    "ground-beef-rustic-pasta-bake",
    "ground-beef-bean-and-greens-bowl",
    "ground-beef-farmhouse-skillet",
    "salmon-market-vegetable-stew",
    "salmon-herb-potato-tray",
    "salmon-rustic-pasta-bake",
    "salmon-bean-and-greens-bowl",
    "salmon-farmhouse-skillet",
    "chicken-taco-bowl",
    "chicken-tortilla-skillet",
    "chicken-lime-rice-plate",
    "chicken-bean-stew",
    "chicken-pepper-fajita-bowl",
    "chicken-enchilada-style-bake",
    "beef-taco-bowl",
    "beef-tortilla-skillet",
    "beef-lime-rice-plate",
    "beef-bean-stew",
    "beef-pepper-fajita-bowl",
    "beef-enchilada-style-bake",
    "black-bean-taco-bowl",
    "black-bean-tortilla-skillet",
    "black-bean-lime-rice-plate",
    "black-bean-bean-stew",
    "black-bean-pepper-fajita-bowl",
    "black-bean-enchilada-style-bake",
    "shrimp-taco-bowl",
    "shrimp-tortilla-skillet",
    "shrimp-lime-rice-plate",
    "shrimp-bean-stew",
    "shrimp-pepper-fajita-bowl",
    "shrimp-enchilada-style-bake",
    "pork-taco-bowl",
    "pork-tortilla-skillet",
    "pork-lime-rice-plate",
    "pork-bean-stew",
    "pork-pepper-fajita-bowl",
    "pork-enchilada-style-bake",
    "lentil-taco-bowl",
    "lentil-tortilla-skillet",
    "lentil-lime-rice-plate",
    "lentil-bean-stew",
    "lentil-pepper-fajita-bowl",
    "lentil-enchilada-style-bake",
    "fish-taco-bowl",
    "fish-tortilla-skillet",
    "fish-lime-rice-plate",
    "fish-bean-stew",
    "fish-pepper-fajita-bowl",
    "fish-enchilada-style-bake",
    "chicken-taco-bowl-mexicanlatin",
    "chicken-tortilla-skillet-mexicanlatin",
    "chicken-lime-rice-plate-mexicanlatin",
    "chicken-coconut-rice-bowl",
    "chicken-plantain-plate",
    "chicken-pepper-stew",
    "chicken-lime-bean-bowl",
    "chicken-island-skillet",
    "beef-coconut-rice-bowl",
    "beef-plantain-plate",
    "beef-pepper-stew",
    "beef-lime-bean-bowl",
    "beef-island-skillet",
    "black-bean-coconut-rice-bowl",
    "black-bean-plantain-plate",
    "black-bean-pepper-stew",
    "black-bean-lime-bean-bowl",
    "black-bean-island-skillet",
    "shrimp-coconut-rice-bowl",
    "shrimp-plantain-plate",
    "shrimp-pepper-stew",
    "shrimp-lime-bean-bowl",
    "shrimp-island-skillet",
    "chicken-curry-rice",
    "chicken-masala-bowl",
    "chicken-dal-plate",
    "chicken-biryani-style-rice",
    "chicken-yogurt-flatbread-plate",
    "chicken-spinach-curry",
    "lentil-curry-rice",
    "lentil-masala-bowl",
    "lentil-dal-plate",
    "lentil-biryani-style-rice",
    "lentil-yogurt-flatbread-plate",
    "lentil-spinach-curry",
    "chickpea-curry-rice",
    "chickpea-masala-bowl",
    "chickpea-dal-plate",
    "chickpea-biryani-style-rice",
    "chickpea-yogurt-flatbread-plate",
    "chickpea-spinach-curry",
    "fish-curry-rice",
    "fish-masala-bowl",
    "fish-dal-plate",
    "fish-biryani-style-rice",
    "fish-yogurt-flatbread-plate",
    "fish-spinach-curry",
    "egg-curry-rice",
    "egg-masala-bowl",
    "egg-dal-plate",
    "egg-biryani-style-rice",
    "egg-yogurt-flatbread-plate",
    "egg-spinach-curry",
    "potato-curry-rice",
    "potato-masala-bowl",
    "potato-dal-plate",
    "potato-biryani-style-rice",
    "potato-yogurt-flatbread-plate",
    "potato-spinach-curry",
    "lamb-curry-rice",
    "lamb-masala-bowl",
    "lamb-dal-plate",
    "lamb-biryani-style-rice",
    "lamb-yogurt-flatbread-plate",
    "lamb-spinach-curry",
    "chicken-curry-rice-southasian",
    "chicken-masala-bowl-southasian",
    "chicken-dal-plate-southasian",
    "chicken-shawarma-bowl",
    "chicken-tahini-rice-plate",
    "chicken-chickpea-stew",
    "chicken-flatbread-dinner",
    "chicken-lemon-herb-skillet",
    "chickpea-shawarma-bowl",
    "chickpea-tahini-rice-plate",
    "chickpea-chickpea-stew",
    "chickpea-flatbread-dinner",
    "chickpea-lemon-herb-skillet",
    "lamb-shawarma-bowl",
    "lamb-tahini-rice-plate",
    "lamb-chickpea-stew",
    "lamb-flatbread-dinner",
    "lamb-lemon-herb-skillet",
    "lentil-shawarma-bowl",
    "lentil-tahini-rice-plate",
    "lentil-chickpea-stew",
    "lentil-flatbread-dinner",
    "lentil-lemon-herb-skillet",
    "eggplant-shawarma-bowl",
    "eggplant-tahini-rice-plate",
    "eggplant-chickpea-stew",
    "eggplant-flatbread-dinner",
    "eggplant-lemon-herb-skillet",
    "fish-shawarma-bowl",
    "fish-tahini-rice-plate",
    "fish-chickpea-stew",
    "fish-flatbread-dinner",
    "fish-lemon-herb-skillet",
    "chicken-couscous-bowl",
    "chicken-harissa-stew",
    "chicken-tagine-style-plate",
    "chicken-chickpea-tomato-bowl",
    "chicken-spiced-vegetable-rice",
    "chickpea-couscous-bowl",
    "chickpea-harissa-stew",
    "chickpea-tagine-style-plate",
    "chickpea-chickpea-tomato-bowl",
    "chickpea-spiced-vegetable-rice",
    "lamb-couscous-bowl",
    "lamb-harissa-stew",
    "lamb-tagine-style-plate",
    "lamb-chickpea-tomato-bowl",
    "lamb-spiced-vegetable-rice",
    "chicken-peanut-style-stew",
    "chicken-tomato-rice-plate",
    "chicken-plantain-bean-bowl",
    "chicken-greens-and-rice-bowl",
    "chicken-spiced-skillet",
    "lentil-peanut-style-stew",
    "lentil-tomato-rice-plate",
    "lentil-plantain-bean-bowl",
    "lentil-greens-and-rice-bowl",
    "lentil-spiced-skillet",
    "black-bean-peanut-style-stew",
    "black-bean-tomato-rice-plate",
    "black-bean-plantain-bean-bowl",
    "black-bean-greens-and-rice-bowl",
    "black-bean-spiced-skillet",
    "fish-peanut-style-stew",
    "fish-tomato-rice-plate",
    "fish-plantain-bean-bowl",
    "fish-greens-and-rice-bowl",
    "fish-spiced-skillet",
    "plantain-peanut-style-stew",
    "plantain-tomato-rice-plate",
    "plantain-plantain-bean-bowl",
    "plantain-greens-and-rice-bowl",
    "plantain-spiced-skillet"
  ]
}
